setup.py
openid_cla/__init__.py
openid_cla/cla.py
python_openid_cla.egg-info/PKG-INFO
python_openid_cla.egg-info/SOURCES.txt
python_openid_cla.egg-info/dependency_links.txt
python_openid_cla.egg-info/requires.txt
python_openid_cla.egg-info/top_level.txt
python_openid_cla.egg-info/zip-safe