Metadata-Version: 1.0
Name: python-openid-cla
Version: 1.0
Summary: This is an implementation of the OpenID cla extension for python-openid
Home-page: http://www.github.com/puiterwijk/python-openid-cla/
Author: Patrick Uiterwijk
Author-email: puiterwijk@gmail.com
License: BSD
Keywords: openid cla
Platform: UNKNOWN
